jupyterlite_p5_kernel/__init__.py
jupyterlite_p5_kernel/_version.py
jupyterlite_p5_kernel-0.1.1.data/data/share/jupyter/labextensions/@jupyterlite/p5-kernel/package.json
jupyterlite_p5_kernel-0.1.1.data/data/share/jupyter/labextensions/@jupyterlite/p5-kernel/static/19df2ee3dbf8f26fd06f05cdf2e6b37c4d582df4a820dbeb756d47aef1512840.png
jupyterlite_p5_kernel-0.1.1.data/data/share/jupyter/labextensions/@jupyterlite/p5-kernel/static/309.1defe0dd2ed55462ff6a.js
jupyterlite_p5_kernel-0.1.1.data/data/share/jupyter/labextensions/@jupyterlite/p5-kernel/static/467.0063efc44051e592b9e9.js
jupyterlite_p5_kernel-0.1.1.data/data/share/jupyter/labextensions/@jupyterlite/p5-kernel/static/528.f4c72ab28c06664089d0.js
jupyterlite_p5_kernel-0.1.1.data/data/share/jupyter/labextensions/@jupyterlite/p5-kernel/static/643.d500ad5bd3432621262b.js
jupyterlite_p5_kernel-0.1.1.data/data/share/jupyter/labextensions/@jupyterlite/p5-kernel/static/remoteEntry.cdbf97db0179334e7548.js
jupyterlite_p5_kernel-0.1.1.data/data/share/jupyter/labextensions/@jupyterlite/p5-kernel/static/style.js
jupyterlite_p5_kernel-0.1.1.data/data/share/jupyter/labextensions/@jupyterlite/p5-kernel/static/third-party-licenses.json
jupyterlite_p5_kernel-0.1.1.data/data/share/jupyter/labextensions/@jupyterlite/p5-kernel/install.json
jupyterlite_p5_kernel-0.1.1.dist-info/METADATA
jupyterlite_p5_kernel-0.1.1.dist-info/WHEEL
jupyterlite_p5_kernel-0.1.1.dist-info/licenses/LICENSE
jupyterlite_p5_kernel-0.1.1.dist-info/RECORD
