Metadata-Version: 2.1
Name: jupyterlite-p5-kernel
Version: 0.1.1
Project-URL: Homepage, https://github.com/jupyterlite/p5-kernel
Project-URL: Bug Tracker, https://github.com/jupyterlite/p5-kernel/issues
Project-URL: Repository, https://github.com/jupyterlite/p5-kernel.git
Author: JupyterLite Contributors
License: BSD 3-Clause License
License-File: LICENSE
Classifier: Framework :: Jupyter
Classifier: License :: OSI Approved :: BSD License
Classifier: Programming Language :: Python
Classifier: Programming Language :: Python :: 3
Classifier: Programming Language :: Python :: 3.7
Classifier: Programming Language :: Python :: 3.8
Classifier: Programming Language :: Python :: 3.9
Classifier: Programming Language :: Python :: 3.10
Classifier: Programming Language :: Python :: 3.11
Requires-Python: >=3.7
